{"Results":{"GeneralInfo":{"Timezone":"RTZ 2 (зима)","CustomFields":{"name":"Mobile Center Server:","value":"http://mc.bell-main.bellintegrator.ru:8080"},"ReportTitle":"LeanFT Report","OrchestrationToolName":"JUnit","RunStartTime":"2018-08-22 22:18:12"},"ReportNode":{"@type":"Run","Data":{"Extension":{"Any":{"IconKey":"Run","IsHtmlErrorText":"true"}},"Description":{"#cdata-section":" "},"ToolName":"LeanFT","StartTime":"2018-08-22 22:18:12","Environment":{"Locale":{"#cdata-section":"ru-RU"},"Timezone":{"#cdata-section":"RTZ 2 (зима)"},"OSInfo":{"#cdata-section":"Microsoft Windows NT 6.2.9200.0"},"User":"VChekusov","NumberOfCores":"8","TotalMemory":"8087","HostName":{"#cdata-section":"NB-704"}},"Duration":{"#cdata-section":"00:01:03.516"},"ToolVersion":{"#cdata-section":"14.03"},"Name":"Run Results","Result":"Passed"},"ReportNode":{"@type":"Package","Data":{"Extension":{"Any":{"IconKey":"Package","IsHtmlErrorText":"true"}},"Description":{"#cdata-section":"Version: N/A"},"StartTime":"2018-08-22 22:18:13","Duration":{"#cdata-section":"00:01:03.183"},"Name":"page","Result":"Passed"},"ReportNode":{"@type":"Class","Data":{"Extension":{"Any":{"IconKey":"Class","IsHtmlErrorText":"true"}},"StartTime":"2018-08-22 22:18:13","Duration":{"#cdata-section":"00:01:03.183"},"Name":{"#cdata-section":"page.YouTubeTest"},"Result":"Passed"},"ReportNode":{"@type":"Test","Data":{"Extension":{"Any":{"IconKey":"Test","IsHtmlErrorText":"true"}},"StartTime":"2018-08-22 22:18:13","Duration":{"#cdata-section":"00:01:03.181"},"Name":"testYouTube","Result":"Passed"},"ReportNode":[{"@type":"CustomStep","Data":{"Extension":{"Any":{"IconKey":"CustomStep","IsHtmlErrorText":"true"}},"Description":{"#cdata-section":"Passed"},"StartTime":"2018-08-22 22:18:22","Duration":{"#cdata-section":"00:00:00.000"},"Name":{"#cdata-section":"Выполнил вход на главную страницу"},"Result":"Passed"}},{"@type":"CustomStep","Data":{"Extension":{"Any":{"IconKey":"CustomStep","IsHtmlErrorText":"true"}},"Description":{"#cdata-section":"Passed"},"StartTime":"2018-08-22 22:19:06","Duration":{"#cdata-section":"00:00:00.000"},"Name":{"#cdata-section":"Загрузка файла завершена"},"Result":"Passed"}},{"@type":"CustomStep","Data":{"Extension":{"Any":{"IconKey":"CustomStep","IsHtmlErrorText":"true"}},"Description":{"#cdata-section":"Passed"},"StartTime":"2018-08-22 22:19:09","Duration":{"#cdata-section":"00:00:00.000"},"Name":{"#cdata-section":"Тест выполнен"},"Result":"Passed"}}]}}}}}}
